efsspysdk/__init__.py
efsspysdk/movie.py
efsspysdk/quote.py
efsspysdk/core/__init__.py
efsspysdk/core/configs/__init__.py
efsspysdk/core/configs/variables.py
efsspysdk/core/models/__init__.py
efsspysdk/core/models/movie.py
efsspysdk/core/models/quote.py
efsspysdk/core/resource/__init__.py
efsspysdk/core/resource/get.py
efsspysdk/core/utils/__init__.py
efsspysdk/core/utils/errors.py
efsspysdk/core/utils/helpers.py
efsspysdk-0.0.3.dist-info/LICENSE
efsspysdk-0.0.3.dist-info/METADATA
efsspysdk-0.0.3.dist-info/WHEEL
efsspysdk-0.0.3.dist-info/top_level.txt
efsspysdk-0.0.3.dist-info/RECORD
