Metadata-Version: 2.1
Name: efsspysdk
Version: 0.0.3
Summary: A SDK for the-one-api.dev API
Author: Emmanuel Felipe Silva Santos
Author-email: hi@emmanuel.cloud
License: MIT License
Requires-Python: >=3.9
License-File: LICENSE
Requires-Dist: pytest
Requires-Dist: requests
